odoo/addons/fieldservice_stage_validation/README.rst
odoo/addons/fieldservice_stage_validation/__init__.py
odoo/addons/fieldservice_stage_validation/__manifest__.py
odoo/addons/fieldservice_stage_validation/i18n/fieldservice_stage_validation.pot
odoo/addons/fieldservice_stage_validation/models/__init__.py
odoo/addons/fieldservice_stage_validation/models/fsm_equipment.py
odoo/addons/fieldservice_stage_validation/models/fsm_location.py
odoo/addons/fieldservice_stage_validation/models/fsm_order.py
odoo/addons/fieldservice_stage_validation/models/fsm_person.py
odoo/addons/fieldservice_stage_validation/models/fsm_stage.py
odoo/addons/fieldservice_stage_validation/readme/CONFIGURE.rst
odoo/addons/fieldservice_stage_validation/readme/CONTRIBUTORS.rst
odoo/addons/fieldservice_stage_validation/readme/DESCRIPTION.rst
odoo/addons/fieldservice_stage_validation/readme/ROADMAP.rst
odoo/addons/fieldservice_stage_validation/readme/USAGE.rst
odoo/addons/fieldservice_stage_validation/static/description/icon.png
odoo/addons/fieldservice_stage_validation/static/description/index.html
odoo/addons/fieldservice_stage_validation/views/fsm_stage.xml
odoo12_addon_fieldservice_stage_validation-12.0.0.2.0.dist-info/METADATA
odoo12_addon_fieldservice_stage_validation-12.0.0.2.0.dist-info/WHEEL
odoo12_addon_fieldservice_stage_validation-12.0.0.2.0.dist-info/top_level.txt
odoo12_addon_fieldservice_stage_validation-12.0.0.2.0.dist-info/RECORD
