Metadata-Version: 2.1
Name: odoo12-addon-fieldservice-stage-validation
Version: 12.0.0.2.0
Summary: Validate input data when reaching a Field Service stage
Home-page: https://github.com/OCA/field-service
Author: Brian McMaster, Odoo Community Association (OCA)
Author-email: support@odoo-community.org
License: AGPL-3
Platform: UNKNOWN
Classifier: Programming Language :: Python
Classifier: Framework :: Odoo
Classifier: License :: OSI Approved :: GNU Affero General Public License v3
Classifier: Development Status :: 4 - Beta
Requires-Python: >=3.5
Requires-Dist: odoo12-addon-fieldservice
Requires-Dist: odoo (<12.1dev,>=12.0a)
